blockie/__init__.py
blockie/blockie.py
blockie-2.0.0.dist-info/licenses/LICENSE
blockie-2.0.0.dist-info/METADATA
blockie-2.0.0.dist-info/WHEEL
blockie-2.0.0.dist-info/top_level.txt
blockie-2.0.0.dist-info/RECORD
