Metadata-Version: 2.4
Name: blockie
Version: 2.0.0
Summary: A lightweight Python template engine
Author-email: Lubomir Milko <lubomir.milko@gmail.com>
License-Expression: GPL-3.0
Project-URL: Repository, https://github.com/lubomilko/blockie
Project-URL: Documentation, https://lubomilko.github.io/blockie/doc/build/html/index.html
Project-URL: Issues, https://github.com/lubomilko/blockie/issues
Classifier: Programming Language :: Python :: 3
Classifier: Operating System :: OS Independent
Classifier: Intended Audience :: Developers
Requires-Python: >=3.12
License-File: LICENSE
Dynamic: license-file
